boldqc/__init__.py
boldqc/__version__.py
boldqc/bids/__init__.py
boldqc/cli/__init__.py
boldqc/cli/get.py
boldqc/cli/process.py
boldqc/cli/tandem.py
boldqc/libexec/helpers.sh
boldqc/libexec/niftiqa.py
boldqc/libexec/niftiqa_wrapper.py
boldqc/libexec/stackcheck_ext.sh
boldqc/parsers/__init__.py
boldqc/state/__init__.py
boldqc/tasks/__init__.py
boldqc/tasks/niftiqa_wrapper.py
boldqc/tasks/stackcheck_ext.py
boldqc/xnat/__init__.py
boldqc-0.5.0.data/scripts/boldQC.py
boldqc-0.5.0.dist-info/licenses/LICENSE
boldqc-0.5.0.dist-info/METADATA
boldqc-0.5.0.dist-info/WHEEL
boldqc-0.5.0.dist-info/top_level.txt
boldqc-0.5.0.dist-info/RECORD
