Metadata-Version: 2.4
Name: boldqc
Version: 0.5.0
Summary: BOLD QC
Home-page: https://github.com/harvard-nrg/boldqc
Author: Neuroinformatics Research Group
Author-email: info@neuroinfo.org
License-File: LICENSE
Requires-Dist: selfie
Requires-Dist: executors
Requires-Dist: yaxil
Requires-Dist: matplotlib
Requires-Dist: nibabel
Requires-Dist: scipy
Dynamic: author
Dynamic: author-email
Dynamic: home-page
Dynamic: license-file
Dynamic: requires-dist
Dynamic: summary
